{"customers":"[{\"id\":\"1\",\"name\":\"Maria Silva\",\"whatsapp\":\"11999998888\",\"address\":\"Rua das Flores, 123, SP\",\"createdAt\":\"2025-11-24T22:51:45.746Z\"},{\"id\":\"2\",\"name\":\"João Santos\",\"whatsapp\":\"21988887777\",\"address\":\"Av Atlantica, 400, RJ\",\"createdAt\":\"2025-11-24T22:51:45.746Z\"}]","products":"[{\"id\":\"1\",\"name\":\"Kit Camisetas Básicas (Caixa 01)\",\"totalQuantity\":100,\"remainingQuantity\":0,\"price\":25,\"status\":\"active\"},{\"id\":\"2\",\"name\":\"Meias Esportivas (Caixa 02)\",\"totalQuantity\":100,\"remainingQuantity\":85,\"price\":12.5,\"status\":\"active\"}]","orders":"[{\"id\":\"101\",\"customerId\":\"1\",\"productId\":\"1\",\"quantity\":10,\"status\":\"Pendente\",\"date\":\"2025-11-24T22:51:45.747Z\",\"isPaid\":true},{\"id\":\"102\",\"customerId\":\"2\",\"productId\":\"2\",\"quantity\":5,\"status\":\"Pendente\",\"date\":\"2025-11-24T22:51:45.747Z\",\"isPaid\":false}]","sellerPhone":""}